{
  "name": "hover-card",
  "type": "registry:ui",
  "description": "A card that appears on hover",
  "dependencies": [],
  "devDependencies": [],
  "registryDependencies": [
    "utils"
  ],
  "files": [
    {
      "path": "ui/hover-card.tsx",
      "content": "import * as React from 'react';\nimport { View, Pressable, Modal, Animated } from 'react-native';\nimport { cn } from '@/lib/utils';\n\ninterface HoverCardProps {\n  children: React.ReactNode;\n}\n\nconst HoverCard = ({ children }: HoverCardProps) => {\n  const [open, setOpen] = React.useState(false);\n  const opacity = React.useRef(new Animated.Value(0)).current;\n  const scale = React.useRef(new Animated.Value(0.95)).current;\n\n  React.useEffect(() => {\n    Animated.parallel([\n      Animated.timing(opacity, {\n        toValue: open ? 1 : 0,\n        duration: 150,\n        useNativeDriver: true,\n      }),\n      Animated.spring(scale, {\n        toValue: open ? 1 : 0.95,\n        useNativeDriver: true,\n      }),\n    ]).start();\n  }, [open]);\n\n  return (\n    <HoverCardContext.Provider value={{ open, setOpen, opacity, scale }}>\n      {children}\n    </HoverCardContext.Provider>\n  );\n};\n\ninterface HoverCardContextValue {\n  open: boolean;\n  setOpen: (open: boolean) => void;\n  opacity: Animated.Value;\n  scale: Animated.Value;\n}\n\nconst HoverCardContext = React.createContext<HoverCardContextValue | null>(null);\n\nconst useHoverCard = () => {\n  const context = React.useContext(HoverCardContext);\n  if (!context) {\n    throw new Error('useHoverCard must be used within HoverCard');\n  }\n  return context;\n};\n\ninterface HoverCardTriggerProps extends React.ComponentPropsWithoutRef<typeof Pressable> {}\n\nconst HoverCardTrigger = React.forwardRef<\n  React.ElementRef<typeof Pressable>,\n  HoverCardTriggerProps\n>(({ className, onPress, onLongPress, ...props }, ref) => {\n  const { setOpen } = useHoverCard();\n\n  return (\n    <Pressable\n      ref={ref}\n      onPress={(e) => {\n        setOpen(true);\n        onPress?.(e);\n      }}\n      onLongPress={(e) => {\n        setOpen(true);\n        onLongPress?.(e);\n      }}\n      className={cn(className)}\n      {...props}\n    />\n  );\n});\nHoverCardTrigger.displayName = 'HoverCardTrigger';\n\ninterface HoverCardContentProps extends React.ComponentPropsWithoutRef<typeof View> {\n  align?: 'start' | 'center' | 'end';\n  sideOffset?: number;\n}\n\nconst HoverCardContent = React.forwardRef<\n  React.ElementRef<typeof View>,\n  HoverCardContentProps\n>(({ className, align = 'center', sideOffset = 4, ...props }, ref) => {\n  const { open, setOpen, opacity, scale } = useHoverCard();\n\n  if (!open) return null;\n\n  return (\n    <Modal\n      transparent\n      visible={open}\n      animationType=\"none\"\n      onRequestClose={() => setOpen(false)}\n    >\n      <Pressable\n        className=\"flex-1 bg-black/50\"\n        onPress={() => setOpen(false)}\n      >\n        <View className=\"flex-1 items-center justify-center p-4\">\n          <Animated.View\n            ref={ref}\n            style={{\n              opacity,\n              transform: [{ scale }],\n            }}\n            className={cn(\n              'z-50 w-64 rounded-md border border-border bg-popover p-4 shadow-md',\n              className\n            )}\n            {...props}\n          />\n        </View>\n      </Pressable>\n    </Modal>\n  );\n});\nHoverCardContent.displayName = 'HoverCardContent';\n\nexport { HoverCard, HoverCardTrigger, HoverCardContent };\n",
      "type": "registry:ui"
    }
  ]
}